{
    "wallpaper": "/home/reorr/Pictures/Unsplash/chris-barbalis-705864-unsplash.jpg",
    "alpha": "100",
    "special": {
        "background": "#f8fbfd",
        "foreground": "#1A2846",
        "cursor": "#1A2846"
    },
    "colors": {
        "color0": "#f8fbfd",
        "color1": "#1C63D3",
        "color2": "#2A69D0",
        "color3": "#057BFA",
        "color4": "#0C8BFE",
        "color5": "#239BEE",
        "color6": "#2599FD",
        "color7": "#1A2846",
        "color8": "#7e8b94",
        "color9": "#1C63D3",
        "color10": "#2A69D0",
        "color11": "#057BFA",
        "color12": "#0C8BFE",
        "color13": "#239BEE",
        "color14": "#2599FD",
        "color15": "#1A2846"
    }
}