{
    "wallpaper": "/home/reorr/Pictures/bg/renders_in_shape/1494800058123.jpg",
    "alpha": "100",
    "special": {
        "background": "#020303",
        "foreground": "#e8e4e4",
        "cursor": "#e8e4e4"
    },
    "colors": {
        "color0": "#020303",
        "color1": "#565E63",
        "color2": "#817E76",
        "color3": "#6392AC",
        "color4": "#5EAFD8",
        "color5": "#989DA0",
        "color6": "#B9C2C6",
        "color7": "#e8e4e4",
        "color8": "#a29f9f",
        "color9": "#565E63",
        "color10": "#817E76",
        "color11": "#6392AC",
        "color12": "#5EAFD8",
        "color13": "#989DA0",
        "color14": "#B9C2C6",
        "color15": "#e8e4e4"
    }
}